swagger_aggregator/__init__.py
swagger_aggregator/swagger_aggregator.py
swagger_aggregator-0.1.1.dist-info/top_level.txt
swagger_aggregator-0.1.1.dist-info/METADATA
swagger_aggregator-0.1.1.dist-info/DESCRIPTION.rst
swagger_aggregator-0.1.1.dist-info/metadata.json
swagger_aggregator-0.1.1.dist-info/WHEEL
swagger_aggregator-0.1.1.dist-info/RECORD
