Metadata-Version: 2.0
Name: swagger-aggregator
Version: 0.1.1
Summary: Aggregate several swagger APIs in one
Home-page: https://github.com/Trax-air/swagger-aggregator
Author: Cyprien Guillemot
Author-email: cyprien.guillemot@gmail.com
License: MIT
Keywords: swagger,aggregator,API,REST,swagger-aggregator
Platform: UNKNOWN
Classifier: Development Status :: 5 - Production/Stable
Classifier: Intended Audience :: Developers
Classifier: License :: OSI Approved :: MIT License
Classifier: Natural Language :: English
Classifier: Programming Language :: Python :: 2
Classifier: Programming Language :: Python :: 2.7
Classifier: Programming Language :: Python :: 3
Classifier: Programming Language :: Python :: 3.3
Classifier: Programming Language :: Python :: 3.4
Requires-Dist: flask (==0.10.1)
Requires-Dist: requests (>=1.8.1)
Requires-Dist: shortuuid (==0.4.3)
Requires-Dist: swagger-parser (==0.1)
Requires-Dist: simplejson (==3.8.1)
Requires-Dist: PyYAML (==3.11)
